<?xml version="1.0" encoding="UTF-8"?>
<xml>

	<NPCModel></NPCModel>
	<AddBaseModel name="shooter" filename="shooter2.elu"> </AddBaseModel>
	<MakeAnimationMap ></MakeAnimationMap>

	<AddAnimation name="idle"		filename="shooter_idle.elu.ani" 	 	gm="1"	motion_type="0" motion_loop_type="loop" > </AddAnimation>
	<AddAnimation name="run"		filename="shooter_run.elu.ani"		gm="1" 	motion_type="0" motion_loop_type="loop" > </AddAnimation>

	<AddAnimation name="suffer1"		filename="shooter_suffer1.elu.ani" 	gm="1"	motion_type="0" motion_loop_type="lastframe" > </AddAnimation>
	<AddAnimation name="suffer2"		filename="shooter_suffer2.elu.ani" 	gm="1"	motion_type="0" motion_loop_type="lastframe" > </AddAnimation>
	<AddAnimation name="suffer3"		filename="shooter_suffer3.elu.ani" 	gm="1"	motion_type="0" motion_loop_type="lastframe" > </AddAnimation>
	<AddAnimation name="suffer3recover"		filename="shooter_suffer3_r.elu.ani" 	gm="1"	motion_type="0" motion_loop_type="lastframe" > </AddAnimation>
	
	<AddAnimation name="retreat"		filename="shooter_retreat.elu.ani" 	gm="1"	motion_type="0" motion_loop_type="lastframe" > </AddAnimation>

	<AddAnimation name="shoot"	filename="shooter_shoot.elu.ani" gm="1" motion_type="0" motion_loop_type="lastframe" > 	</AddAnimation>
	<AddAnimation name="shootup"	filename="shooter_shootup.elu.ani" gm="1" motion_type="0" motion_loop_type="lastframe" > 	</AddAnimation>
	
	<AddAnimation name="lightningstun"		filename="shooter_lightning.elu.ani"  gm="1"	motion_type="0" motion_loop_type="loop" > </AddAnimation>
	<AddAnimation name="blast_soar"		filename="shooter_blast.elu.ani" 	 gm="1"	motion_type="0" motion_loop_type="lastframe" > 	</AddAnimation>
	<AddAnimation name="blast_fall"		filename="shooter_blast_fall.elu.ani" 	gm="1"	motion_type="0" motion_loop_type="lastframe" > </AddAnimation>
	<AddAnimation name="blast_down"		filename="shooter_blast_drop.elu.ani" 	gm="1"	motion_type="0" motion_loop_type="lastframe" > </AddAnimation>
	<AddAnimation name="standup"		filename="shooter_blast_stand.elu.ani" 	 gm="1"	motion_type="0" motion_loop_type="lastframe" > </AddAnimation>
	<AddAnimation name="blast_thrust"	filename="shooter_blast_dagger.elu.ani" 	 gm="1"	motion_type="0" motion_loop_type="lastframe" > </AddAnimation>
	<AddAnimation name="blast_thrustdown" filename="shooter_blast_drop_dagger.elu.ani" 	 gm="1"	motion_type="0" motion_loop_type="lastframe" > </AddAnimation>
	<AddAnimation name="die"		filename="shooter_die.elu.ani"		gm="1"	motion_type="0" motion_loop_type="lastframe" 	> 	</AddAnimation>


</xml>
